continuous_cmap/__init__.py
continuous_cmap/_modidx.py
continuous_cmap/cmap.py
continuous_cmap-0.0.6.dist-info/LICENSE
continuous_cmap-0.0.6.dist-info/METADATA
continuous_cmap-0.0.6.dist-info/WHEEL
continuous_cmap-0.0.6.dist-info/entry_points.txt
continuous_cmap-0.0.6.dist-info/top_level.txt
continuous_cmap-0.0.6.dist-info/RECORD
