Metadata-Version: 2.1
Name: continuous-cmap
Version: 0.0.6
Summary: Create a continuous colormap in matplotlib
Home-page: https://github.com/CJP123/continuous_cmap/
Author: Clive
Author-email: clive@gm.net.nz
License: Apache Software License 2.0
Keywords: nbdev
Classifier: Development Status :: 3 - Alpha
Classifier: Intended Audience :: Developers
Classifier: Natural Language :: English
Classifier: Programming Language :: Python :: 3.9
Classifier: Programming Language :: Python :: 3.10
Classifier: License :: OSI Approved :: Apache Software License
Requires-Python: >=3.9
License-File: LICENSE
Requires-Dist: fastcore
Requires-Dist: pandas
Requires-Dist: matplotlib
Provides-Extra: dev
